[
  {
    "id": "prj-1777128277500",
    "title": "Knowledge Hub HTML",
    "description": "Standalone HTML knowledge hub",
    "url": "./pkg-battery-knowledge-hub/index.html",
    "badge": "HTML",
    "color": "bg-yellow-600",
    "category": "Bài viết",
    "createdAt": "2026-04-25T14:44:37.500Z"
  },
  {
    "id": "prj-67",
    "title": "Knowledge Hub v1.7",
    "description": "Premium B2B Knowledge Hub v2 — editorial hero, sticky filter tabs, featured grid, trust strip, editorial rows, compact news list, topic clusters, dark case study showcase, final CTA, mobile bottom bar. Industrial luxury direction.",
    "url": "./knowledge-hub-v2/index.html",
    "badge": "Vanilla HTML/CSS/JS",
    "color": "bg-red-900",
    "category": "Bài viết",
    "createdAt": "2026-04-25T18:20:00Z",
    "rating": 3
  },
  {
    "id": "prj-66",
    "title": "Knowledge Hub v1.6",
    "description": "Premium B2B Knowledge Hub / Article Listing Page — hero search, category filters, featured editorial layout, article grid, download resources, case studies, trust strip, final CTA. Industrial luxury direction.",
    "url": "./knowledge-hub/index.html",
    "badge": "Vanilla HTML/CSS/JS",
    "color": "bg-red-900",
    "category": "Bài viết",
    "createdAt": "2026-04-25T16:30:00Z",
    "rating": 3
  },
  {
    "id": "prj-65",
    "title": "Chi tiết sản phẩm v1.9",
    "description": "Bản React build từ file zip",
    "url": "./product-detail-v1-9/index.html",
    "badge": "React",
    "color": "bg-blue-600",
    "category": "Chi tiết sản phẩm",
    "createdAt": "2026-04-25T14:49:09Z"
  },
  {
    "id": "prj-64",
    "title": "Chi tiết sản phẩm v1.8",
    "description": "Bản React build từ file zip",
    "url": "./product-detail-v1-8/index.html",
    "badge": "React",
    "color": "bg-blue-600",
    "category": "Chi tiết sản phẩm",
    "createdAt": "2026-04-25T14:49:08Z"
  },
  {
    "id": "prj-63",
    "title": "Chi tiết sản phẩm v1.7",
    "description": "Bản React build từ file zip",
    "url": "./product-detail-v1-7/index.html",
    "badge": "React",
    "color": "bg-blue-600",
    "category": "Chi tiết sản phẩm",
    "createdAt": "2026-04-25T14:49:07Z"
  },
  {
    "id": "prj-62",
    "title": "Chi tiết sản phẩm v1.6",
    "description": "Bản React build từ file zip",
    "url": "./product-detail-v1-6/index.html",
    "badge": "React",
    "color": "bg-blue-600",
    "category": "Chi tiết sản phẩm",
    "createdAt": "2026-04-25T14:49:06Z"
  },
  {
    "id": "prj-61",
    "title": "Chi tiết sản phẩm v1.5",
    "description": "Bản React build từ file zip",
    "url": "./product-detail-v1-5/index.html",
    "badge": "React",
    "color": "bg-blue-600",
    "category": "Chi tiết sản phẩm",
    "createdAt": "2026-04-25T14:49:05Z"
  },
  {
    "id": "prj-60",
    "title": "Chi tiết sản phẩm v1.4",
    "description": "Bản React build từ file zip",
    "url": "./product-detail-v1-4/index.html",
    "badge": "React",
    "color": "bg-blue-600",
    "category": "Chi tiết sản phẩm",
    "createdAt": "2026-04-25T14:49:04Z"
  },
  {
    "id": "prj-59",
    "title": "Chi tiết sản phẩm v1.3",
    "description": "Bản React build từ file zip",
    "url": "./product-detail-v1-3/index.html",
    "badge": "React",
    "color": "bg-blue-600",
    "category": "Chi tiết sản phẩm",
    "createdAt": "2026-04-25T14:49:03Z"
  },
  {
    "id": "prj-58",
    "title": "Chi tiết sản phẩm v1.2",
    "description": "Bản React build từ file zip",
    "url": "./product-detail-v1-2/index.html",
    "badge": "React",
    "color": "bg-blue-600",
    "category": "Chi tiết sản phẩm",
    "createdAt": "2026-04-25T14:49:02Z"
  },
  {
    "id": "prj-57",
    "title": "Chi tiết sản phẩm v1.0 (React)",
    "description": "Bản React build từ file zip",
    "url": "./product-detail-v1-0/index.html",
    "badge": "React",
    "color": "bg-blue-600",
    "category": "Chi tiết sản phẩm",
    "createdAt": "2026-04-25T14:49:01Z"
  },
  {
    "id": "prj-56",
    "title": "Chi tiết sản phẩm v1.1",
    "description": "Bản cập nhật HTML do người dùng cung cấp từ OneDrive.",
    "url": "./product-detail-v1-1/index.html",
    "badge": "HTML",
    "color": "bg-red-800",
    "category": "Chi tiết sản phẩm",
    "createdAt": "2026-04-25T14:43:00Z"
  },
  {
    "id": "prj-17771280350987",
    "title": "Bài viết v1.5",
    "description": "Bản React build từ file zip",
    "url": "./bai-viet-v1-5/index.html",
    "badge": "React",
    "color": "bg-blue-600",
    "category": "Bài viết",
    "createdAt": "2026-04-25T14:40:35.098Z",
    "rating": 5
  },
  {
    "id": "prj-17771280350986",
    "title": "Bài viết v1.4",
    "description": "Bản React build từ file zip",
    "url": "./bai-viet-v1-4/index.html",
    "badge": "React",
    "color": "bg-blue-600",
    "category": "Bài viết",
    "createdAt": "2026-04-25T14:40:35.098Z"
  },
  {
    "id": "prj-17771280350985",
    "title": "Bài viết v1.3",
    "description": "Bản React build từ file zip",
    "url": "./bai-viet-v1-3/index.html",
    "badge": "React",
    "color": "bg-blue-600",
    "category": "Bài viết",
    "createdAt": "2026-04-25T14:40:35.098Z"
  },
  {
    "id": "prj-17771280350984",
    "title": "Bài viết v1.2.1",
    "description": "Bản React build từ file zip",
    "url": "./bai-viet-v1-2-1/index.html",
    "badge": "React",
    "color": "bg-blue-600",
    "category": "Bài viết",
    "createdAt": "2026-04-25T14:40:35.098Z"
  },
  {
    "id": "prj-17771280350983",
    "title": "Bài viết v1.2",
    "description": "Bản React build từ file zip",
    "url": "./bai-viet-v1-2/index.html",
    "badge": "React",
    "color": "bg-blue-600",
    "category": "Bài viết",
    "createdAt": "2026-04-25T14:40:35.098Z"
  },
  {
    "id": "prj-17771280350982",
    "title": "Bài viết v1.1",
    "description": "Bản React build từ file zip",
    "url": "./bai-viet-v1-1/index.html",
    "badge": "React",
    "color": "bg-blue-600",
    "category": "Bài viết",
    "createdAt": "2026-04-25T14:40:35.098Z"
  },
  {
    "id": "prj-17771280350981",
    "title": "Bài viết v1.0",
    "description": "Bản React build từ file zip",
    "url": "./bai-viet-v1-0/index.html",
    "badge": "React",
    "color": "bg-blue-600",
    "category": "Bài viết",
    "createdAt": "2026-04-25T14:40:35.098Z"
  },
  {
    "id": "prj-55",
    "title": "Chi tiết sản phẩm v3.0",
    "description": "Premium B2B product detail — hero product stage with square image, thumbnail gallery, spec dashboard with dividers, editorial benefits, use-case selector, square gallery grid with lightbox nav, flexible body content, sticky header specs table, product family grid, document center, warranty callout+accordion, related grid, RFQ form, desktop sidebar + mobile bottom sticky CTA.",
    "url": "./product-detail-v3/index.html",
    "badge": "Vanilla HTML/CSS/JS",
    "color": "bg-red-900",
    "category": "Chi tiết sản phẩm",
    "createdAt": "2026-04-25T11:35:00Z",
    "rating": 5
  },
  {
    "id": "prj-54",
    "title": "Chi tiết sản phẩm v2.0",
    "description": "Full-spec B2B product detail page — 17 sections: Hero, Spec Dashboard, Gallery, Benefits, Applications, Compatibility, Tech/BMS, Specs Table, Product Family, Downloads, Warranty, Certifications, FAQ, Related, RFQ Form, Contact Short, Sticky CTA.",
    "url": "./product-detail-v2/index.html",
    "badge": "Vanilla HTML/CSS/JS",
    "color": "bg-red-900",
    "category": "Chi tiết sản phẩm",
    "createdAt": "2026-04-25T11:30:00Z",
    "rating": 5
  },
  {
    "id": "prj-53",
    "title": "Chi tiết sản phẩm v1.0",
    "description": "Trang chi tiết sản phẩm pin lithium PKGFF-24230V1 — 13 sections, B2B industrial luxury, spec dashboard, product family nav, document library, warranty accordion, contact form.",
    "url": "./product-detail-v1/index.html",
    "badge": "Vanilla HTML/CSS/JS",
    "color": "bg-red-900",
    "category": "Chi tiết sản phẩm",
    "createdAt": "2026-04-25T10:00:00Z",
    "rating": 5
  },
  {
    "id": "prj-52",
    "title": "Trust Section v1.6",
    "description": "Partner trust section v1.6 — clean React+Vite build, minimal dependency footprint, latest iteration of the PKG trust/partner showcase component.",
    "url": "./trust-section-v1-6/index.html",
    "badge": "React",
    "color": "bg-emerald-700",
    "category": "Trust",
    "createdAt": "2026-04-23T22:00:00Z",
    "rating": 3
  },
  {
    "id": "prj-51",
    "title": "Trust Section v1.5",
    "description": "Partner trust section v1.5 — streamlined component layout, React+Vite, refined partner logo marquee and social-proof elements.",
    "url": "./trust-section-v1-5/index.html",
    "badge": "React",
    "color": "bg-emerald-600",
    "category": "Trust",
    "createdAt": "2026-04-23T21:00:00Z",
    "rating": 2
  },
  {
    "id": "prj-50",
    "title": "Trust Section v1.4",
    "description": "Partner trust section v1.4 — React+Vite with background effects, partner logo carousel, and animated trust indicators.",
    "url": "./trust-section-v1-4/index.html",
    "badge": "React",
    "color": "bg-emerald-500",
    "category": "Trust",
    "createdAt": "2026-04-23T20:00:00Z",
    "rating": 4,
    "flagged": true
  },
  {
    "id": "prj-49",
    "title": "Trust Section v1.2",
    "description": "Trust & partner section v1.2 — Figma Make export with full shadcn/ui stack, polished partner logo grid and credential badges.",
    "url": "./trust-section-v1-2/index.html",
    "badge": "Figma Make",
    "color": "bg-fuchsia-700",
    "category": "Trust",
    "createdAt": "2026-04-23T19:00:00Z",
    "rating": 4,
    "flagged": true
  },
  {
    "id": "prj-48",
    "title": "Trust Section v1.1",
    "description": "Trust & partner section v1.1 — Figma Make export, refined layout with updated partner logo placement and trust copy.",
    "url": "./trust-section-v1-1/index.html",
    "badge": "Figma Make",
    "color": "bg-fuchsia-600",
    "category": "Trust",
    "createdAt": "2026-04-23T18:00:00Z",
    "rating": 3
  },
  {
    "id": "prj-47",
    "title": "Trust Section v1.0",
    "description": "Trust & partner section v1.0 — initial Figma Make export, full shadcn/ui component set, partner logos marquee, PKG certification badges.",
    "url": "./trust-section-v1-0/index.html",
    "badge": "Figma Make",
    "color": "bg-fuchsia-500",
    "category": "Trust",
    "createdAt": "2026-04-23T17:00:00Z",
    "rating": 4
  },
  {
    "id": "prj-31",
    "title": "PKG Industrial v1.0",
    "description": "Industrial-focused B2B landing page — 12+ sections, technical grid aesthetics, OEM/ODM focus, interactive dealer map, cinematic hero.",
    "url": "./pkg-industrial-v1/index.html",
    "badge": "Vanilla HTML/CSS/JS",
    "color": "bg-red-900",
    "category": "Homepage",
    "rating": 3,
    "createdAt": "2026-04-23T16:00:00Z"
  },
  {
    "badge": "Vanilla HTML/CSS/JS",
    "id": "prj-30",
    "category": "Homepage",
    "color": "bg-red-800",
    "title": "Homepage B2B v3 — Flagship",
    "url": "./homepage-b2b-v3/index.html",
    "description": "17-section world-class B2B flagship homepage — Trust-first, 5-product showcase, OEM/ODM, dealer map, news, case studies, cinematic hero. Industrial Luxury direction.",
    "rating": 5,
    "createdAt": "2026-04-23T15:00:00Z"
  },
  {
    "badge": "Vanilla HTML/CSS/JS",
    "id": "prj-29",
    "category": "Homepage",
    "color": "bg-red-700",
    "title": "Homepage B2B v2",
    "url": "./homepage-b2b-v2/index.html",
    "description": "Strategic B2B homepage v2 — 9 cinematic dark sections, trust-first architecture, pain-point framework, application showcase, process timeline, premium form CTA. Industrial Luxury direction.",
    "rating": 4,
    "createdAt": "2026-04-23T14:00:00Z"
  },
  {
    "badge": "Vanilla HTML/CSS/JS",
    "id": "prj-28",
    "category": "Homepage",
    "color": "bg-red-600",
    "title": "Homepage V1.3 - Codex",
    "url": "./pkg-homepage-b2b/index.html",
    "description": "Trust-first flagship homepage — warm editorial light palette, consultative B2B messaging, consultative CTA. Previous version.",
    "rating": 2,
    "createdAt": "2026-04-23T13:00:00Z"
  },
  {
    "id": "prj-20",
    "title": "Giới Thiệu Công Ty v1.7",
    "description": "World-class enterprise landing page — Premium corporate identity, 12 cinematic sections, interactive Vietnam network map, scroll animations.",
    "url": "./pkg-corporate/index.html",
    "badge": "Vanilla HTML/CSS/JS",
    "color": "bg-red-500",
    "category": "Giới thiệu công ty",
    "rating": 4,
    "createdAt": "2026-04-23T12:00:00Z"
  },
  {
    "id": "prj-27",
    "title": "Giới Thiệu Công Ty v1.6",
    "description": "Trang giới thiệu công ty PKG Battery — phiên bản v1.6.",
    "url": "./gioi-thieu-cong-ty-v1-6/index.html",
    "badge": "React",
    "color": "bg-indigo-600",
    "category": "Giới thiệu công ty",
    "rating": 5,
    "createdAt": "2026-04-23T11:00:00Z"
  },
  {
    "id": "prj-26",
    "title": "Giới Thiệu Công Ty v1.5",
    "description": "Trang giới thiệu công ty PKG Battery — phiên bản v1.5.",
    "url": "./gioi-thieu-cong-ty-v1-5/index.html",
    "badge": "React",
    "color": "bg-indigo-600",
    "category": "Giới thiệu công ty",
    "rating": 5,
    "createdAt": "2026-04-23T10:00:00Z"
  },
  {
    "id": "prj-25",
    "title": "Giới Thiệu Công Ty v1.4",
    "description": "Trang giới thiệu công ty PKG Battery — phiên bản v1.4.",
    "url": "./gioi-thieu-cong-ty-v1-4/index.html",
    "badge": "React",
    "color": "bg-indigo-600",
    "category": "Giới thiệu công ty",
    "rating": 4,
    "createdAt": "2026-04-23T09:00:00Z"
  },
  {
    "id": "prj-24",
    "title": "Giới Thiệu Công Ty v1.3",
    "description": "Button shadow đẹp",
    "url": "./gioi-thieu-cong-ty-v1-3/index.html",
    "badge": "React",
    "color": "bg-indigo-600",
    "category": "Giới thiệu công ty",
    "rating": 5,
    "createdAt": "2026-04-23T08:00:00Z"
  },
  {
    "id": "prj-23",
    "title": "Giới Thiệu Công Ty v1.2",
    "description": "Trang giới thiệu công ty PKG Battery — phiên bản v1.2.",
    "url": "./gioi-thieu-cong-ty-v1-2/index.html",
    "badge": "React",
    "color": "bg-indigo-600",
    "category": "Giới thiệu công ty",
    "rating": 4,
    "createdAt": "2026-04-23T07:00:00Z"
  },
  {
    "id": "prj-22",
    "title": "Giới Thiệu Công Ty v1.1",
    "description": "Button ổn",
    "url": "./gioi-thieu-cong-ty-v1-1/index.html",
    "badge": "Figma Make",
    "color": "bg-fuchsia-600",
    "category": "Giới thiệu công ty",
    "rating": 4,
    "createdAt": "2026-04-23T06:00:00Z"
  },
  {
    "id": "prj-21",
    "title": "Giới Thiệu Công Ty v1.0",
    "description": "Trang giới thiệu công ty PKG Battery — phiên bản v1.0, Figma Make export.",
    "url": "./gioi-thieu-cong-ty-v1-0/index.html",
    "badge": "Figma Make",
    "color": "bg-fuchsia-600",
    "category": "Giới thiệu công ty",
    "rating": 4,
    "createdAt": "2026-04-23T05:00:00Z"
  },
  {
    "id": "prj-16",
    "title": "Warranty System",
    "description": "PKG Battery warranty system interface.",
    "url": "./warranty-system/index.html",
    "badge": "React",
    "color": "bg-violet-600",
    "category": "Bảo hành",
    "createdAt": "2026-04-23T04:00:00Z"
  },
  {
    "id": "prj-19",
    "title": "Chính sách bảo hành",
    "description": "PKG Warranty premium industrial experience page.",
    "url": "./warranty-premium-industrial/index.html",
    "badge": "React",
    "color": "bg-orange-600",
    "category": "Bảo hành",
    "createdAt": "2026-04-23T03:00:00Z"
  },
  {
    "id": "prj-17",
    "title": "Warranty Premium Service",
    "description": "PKG Battery warranty premium service page.",
    "url": "./warranty-premium-service/index.html",
    "badge": "React",
    "color": "bg-amber-600",
    "category": "Bảo hành",
    "createdAt": "2026-04-23T02:00:00Z"
  },
  {
    "id": "prj-15",
    "title": "Premium Warranty Experience",
    "description": "PKG Battery premium warranty experience page.",
    "url": "./premium-warranty-experience/index.html",
    "badge": "React",
    "color": "bg-rose-600",
    "category": "Bảo hành",
    "rating": 3,
    "createdAt": "2026-04-23T01:00:00Z"
  },
  {
    "id": "prj-18",
    "title": "Warranty Policy (New)",
    "description": "PKG Battery warranty policy — new version.",
    "url": "./warranty-policy-new/index.html",
    "badge": "React",
    "color": "bg-teal-600",
    "category": "Bảo hành",
    "createdAt": "2026-04-23T00:00:00Z"
  },
  {
    "id": "prj-9",
    "title": "Warranty Policy v1.4",
    "description": "Alternate React layout from source bundle.",
    "url": "./warranty-policy-1-4/index.html",
    "badge": "React",
    "color": "bg-fuchsia-600",
    "category": "Bảo hành",
    "createdAt": "2026-04-22T23:00:00Z"
  },
  {
    "id": "prj-8",
    "title": "Warranty Policy v1.3",
    "description": "Alternate React layout from source bundle.",
    "url": "./warranty-policy-1-3/index.html",
    "badge": "React",
    "color": "bg-fuchsia-600",
    "category": "Bảo hành",
    "createdAt": "2026-04-22T22:00:00Z"
  },
  {
    "id": "prj-7",
    "title": "Warranty Policy v1.2",
    "description": "Alternate React layout from source bundle.",
    "url": "./warranty-policy-1-2/index.html",
    "badge": "React",
    "color": "bg-fuchsia-600",
    "category": "Bảo hành",
    "createdAt": "2026-04-22T21:00:00Z"
  },
  {
    "id": "prj-6",
    "title": "Warranty Policy v1.1",
    "description": "Alternate React layout from source bundle.",
    "url": "./warranty-policy-1-1/index.html",
    "badge": "React",
    "color": "bg-fuchsia-600",
    "category": "Bảo hành",
    "createdAt": "2026-04-22T20:00:00Z"
  },
  {
    "id": "prj-5",
    "title": "Warranty Policy v4",
    "description": "Cinematic premium version of the warranty policy.",
    "url": "./warranty-policy-v4/index.html",
    "badge": "Vanilla HTML/CSS",
    "color": "bg-emerald-600",
    "category": "Bảo hành",
    "createdAt": "2026-04-22T19:00:00Z"
  },
  {
    "id": "prj-4",
    "title": "Warranty Policy v3",
    "description": "Updated layout with different card structure.",
    "url": "./warranty-policy-v3/index.html",
    "badge": "Vanilla HTML/CSS",
    "color": "bg-yellow-600",
    "category": "Bảo hành",
    "createdAt": "2026-04-22T18:00:00Z"
  },
  {
    "id": "prj-3",
    "title": "Warranty Policy v2",
    "description": "Dark mode standard version of the warranty policy.",
    "url": "./warranty-policy-v2/index.html",
    "badge": "Vanilla HTML/CSS",
    "color": "bg-yellow-600",
    "category": "Bảo hành",
    "createdAt": "2026-04-22T17:00:00Z"
  },
  {
    "id": "prj-2",
    "title": "Warranty Policy v1",
    "description": "Original legacy version of the warranty policy page.",
    "url": "./warranty-policy/index.html",
    "badge": "Vanilla HTML/CSS",
    "color": "bg-yellow-600",
    "category": "Bảo hành",
    "flagged": false,
    "createdAt": "2026-04-22T16:00:00Z"
  },
  {
    "id": "prj-13",
    "title": "Product Overview v1.4",
    "description": "Interactive product overview layout from source bundle.",
    "url": "./product-overview-1-4/index.html",
    "badge": "React",
    "color": "bg-cyan-600",
    "category": "Tổng quan sản phẩm",
    "createdAt": "2026-04-22T15:00:00Z",
    "rating": 4
  },
  {
    "id": "prj-12",
    "title": "Product Overview v1.3",
    "description": "Interactive product overview layout from source bundle.",
    "url": "./product-overview-1-3/index.html",
    "badge": "React",
    "color": "bg-cyan-600",
    "category": "Tổng quan sản phẩm",
    "createdAt": "2026-04-22T14:00:00Z",
    "rating": 4
  },
  {
    "id": "prj-11",
    "title": "Product Overview v1.2",
    "description": "Interactive product overview layout from source bundle.",
    "url": "./product-overview-1-2/index.html",
    "badge": "React",
    "color": "bg-cyan-600",
    "category": "Tổng quan sản phẩm",
    "rating": 4,
    "createdAt": "2026-04-22T13:00:00Z"
  },
  {
    "id": "prj-46",
    "title": "Industrial Lithium Solutions",
    "description": "Hero đẹp\n2* nội dung vì thiếu nội dung section",
    "url": "./pkg-industrial-lithium-solutions/index.html",
    "badge": "React",
    "color": "bg-blue-600",
    "category": "Dòng sản phẩm",
    "createdAt": "2026-04-22T12:30:13Z",
    "rating": 4
  },
  {
    "id": "prj-45",
    "title": "Giới Thiệu Công Ty v1.11 - Hero",
    "description": "Corporate introduction variation v1.11 with hero section focus.",
    "url": "./gioi-thieu-cong-ty-v1-11-hero/index.html",
    "badge": "React",
    "color": "bg-indigo-900",
    "category": "Giới thiệu công ty",
    "createdAt": "2026-04-22T12:30:12Z",
    "rating": 3
  },
  {
    "id": "prj-44",
    "title": "Giới Thiệu Công Ty v1.10 - Hero",
    "description": "Corporate introduction variation v1.10 with hero section focus.",
    "url": "./gioi-thieu-cong-ty-v1-10-hero/index.html",
    "badge": "React",
    "color": "bg-indigo-800",
    "category": "Giới thiệu công ty",
    "createdAt": "2026-04-22T12:30:11Z",
    "rating": 4
  },
  {
    "id": "prj-43",
    "title": "Giới Thiệu Công Ty v1.9 - Hero",
    "description": "Corporate introduction variation v1.9 with hero section focus.",
    "url": "./gioi-thieu-cong-ty-v1-9-hero/index.html",
    "badge": "React",
    "color": "bg-indigo-700",
    "category": "Giới thiệu công ty",
    "createdAt": "2026-04-22T12:30:10Z",
    "rating": 3
  },
  {
    "id": "prj-42",
    "title": "Giới Thiệu Công Ty v1.8 - Hero",
    "description": "Corporate introduction variation v1.8 with hero section focus.",
    "url": "./gioi-thieu-cong-ty-v1-8-hero/index.html",
    "badge": "React",
    "color": "bg-indigo-600",
    "category": "Giới thiệu công ty",
    "createdAt": "2026-04-22T12:30:09Z",
    "rating": 4
  },
  {
    "id": "prj-41",
    "title": "Homepage v1.14",
    "description": "Strategic homepage variation v1.14.",
    "url": "./homepage-v1-14/index.html",
    "badge": "React",
    "color": "bg-orange-900",
    "category": "Homepage",
    "createdAt": "2026-04-22T12:30:08Z",
    "rating": 5
  },
  {
    "id": "prj-40",
    "title": "Homepage v1.13",
    "description": "Strategic homepage variation v1.13.",
    "url": "./homepage-v1-13/index.html",
    "badge": "React",
    "color": "bg-orange-800",
    "category": "Homepage",
    "createdAt": "2026-04-22T12:30:07Z",
    "rating": 5
  },
  {
    "id": "prj-39",
    "title": "Homepage v1.12",
    "description": "Strategic homepage variation v1.12.",
    "url": "./homepage-v1-12/index.html",
    "badge": "React",
    "color": "bg-orange-700",
    "category": "Homepage",
    "createdAt": "2026-04-22T12:30:06Z",
    "rating": 5
  },
  {
    "id": "prj-38",
    "title": "Homepage v1.11",
    "description": "Strategic homepage variation v1.11.",
    "url": "./homepage-v1-11/index.html",
    "badge": "React",
    "color": "bg-orange-600",
    "category": "Homepage",
    "createdAt": "2026-04-22T12:30:05Z",
    "rating": 3
  },
  {
    "id": "prj-37",
    "title": "Homepage v1.10",
    "description": "Strategic homepage variation v1.10.",
    "url": "./homepage-v1-10/index.html",
    "badge": "React",
    "color": "bg-red-900",
    "category": "Homepage",
    "createdAt": "2026-04-22T12:30:04Z",
    "rating": 4
  },
  {
    "id": "prj-36",
    "title": "Homepage v1.9",
    "description": "Strategic homepage variation v1.9.",
    "url": "./homepage-v1-9/index.html",
    "badge": "React",
    "color": "bg-red-800",
    "category": "Homepage",
    "createdAt": "2026-04-22T12:30:03Z",
    "rating": 5
  },
  {
    "id": "prj-35",
    "title": "Homepage v1.7",
    "description": "Strategic homepage variation v1.7.",
    "url": "./homepage-v1-7/index.html",
    "badge": "React",
    "color": "bg-red-700",
    "category": "Homepage",
    "createdAt": "2026-04-22T12:30:02Z",
    "rating": 4
  },
  {
    "id": "prj-34",
    "title": "Homepage v1.6",
    "description": "Strategic homepage variation v1.6.",
    "url": "./homepage-v1-6/index.html",
    "badge": "React",
    "color": "bg-red-600",
    "category": "Homepage",
    "createdAt": "2026-04-22T12:30:01Z",
    "rating": 3
  },
  {
    "id": "prj-33",
    "title": "Homepage v1.5",
    "description": "Strategic homepage variation v1.5.",
    "url": "./homepage-v1-5/index.html",
    "badge": "React",
    "color": "bg-red-500",
    "category": "Homepage",
    "createdAt": "2026-04-22T12:30:00Z",
    "rating": 4
  },
  {
    "id": "prj-10",
    "title": "Product Overview v1.1",
    "description": "Interactive product overview layout from source bundle.",
    "url": "./product-overview-1-1/index.html",
    "badge": "React",
    "color": "bg-cyan-600",
    "category": "Tổng quan sản phẩm",
    "createdAt": "2026-04-22T12:00:00Z",
    "rating": 4
  },
  {
    "id": "prj-14",
    "title": "Dòng sản phẩm",
    "description": "Flagship landing page for AeroStream Stratos Series.",
    "url": "./aerostream-stratos/index.html",
    "badge": "React",
    "color": "bg-indigo-600",
    "category": "Dòng sản phẩm",
    "createdAt": "2026-04-22T11:00:00Z"
  },
  {
    "id": "prj-1",
    "title": "Dòng sản phẩm",
    "description": "React + Tailwind App for Lithium Battery Sightseeing Vehicles.",
    "url": "./lithium-sightseeing/index.html",
    "badge": "React",
    "color": "bg-blue-600",
    "category": "Dòng sản phẩm",
    "createdAt": "2026-04-22T10:00:00Z"
  },
  {
    "badge": "Vanilla HTML/CSS/JS",
    "id": "prj-32",
    "category": "Homepage",
    "color": "bg-rose-700",
    "title": "Homepage B2B v4 - Provided HTML",
    "url": "./homepage-b2b-v4/index.html",
    "description": "Homepage B2B v4 from provided HTML - industrial dark direction, 5 solution groups, OEM/ODM, dealer network, news, and consultation CTA.",
    "createdAt": "2026-04-22T10:00:00Z",
    "rating": 3
  }
]